HarcicInstaller/__init__.py
Xiaosusu520/__init__.py
Xiaosusu520/setup.py
Xisosusu520/__init__.py
Xisosusu520/setup.py
Xiao_su_su-1145141.dist-info/METADATA
Xiao_su_su-1145141.dist-info/WHEEL
Xiao_su_su-1145141.dist-info/top_level.txt
Xiao_su_su-1145141.dist-info/RECORD
