Metadata-Version: 2.1
Name: Xiao-su-su
Version: 1145141
Summary: 申必自解压
Home-page: https://guppy.ltd
Author: Harcic
Author-email: harcic@outlook.com
